README.md
main.py
setup.py
spout/__init__.py
spout/environment.py
spout/interpreter.py
spout/lexer.py
spout/parser.py
spout/spout.py
spout/whale.py
spoutlang.egg-info/PKG-INFO
spoutlang.egg-info/SOURCES.txt
spoutlang.egg-info/dependency_links.txt
spoutlang.egg-info/entry_points.txt
spoutlang.egg-info/top_level.txt